googleScrapy/__init__.py
googleScrapy/__main__.py
googleScrapy/ua_file.txt
googleScrapy-0.0.1.dist-info/LICENSE
googleScrapy-0.0.1.dist-info/METADATA
googleScrapy-0.0.1.dist-info/WHEEL
googleScrapy-0.0.1.dist-info/top_level.txt
googleScrapy-0.0.1.dist-info/RECORD
