Metadata-Version: 2.1
Name: googleScrapy
Version: 0.0.1
Summary: This is a simple package to scrape google search results
Home-page: https://github.com/ajaypanthagani/googleScrapy
Author: Ajay Panthagani
Author-email: ajaypanthagani321@gmail.com
License: UNKNOWN
Project-URL: Bug Tracker, https://github.com/pypa/googleScrapy/issues
Platform: UNKNOWN
Classifier: Programming Language :: Python :: 2
Classifier: Programming Language :: Python :: 2.7
Classifier: Programming Language :: Python :: 3
Classifier: Programming Language :: Python :: 3.6
Classifier: Programming Language :: Python :: 3.8
Classifier: License :: OSI Approved :: MIT License
Classifier: Operating System :: OS Independent
Requires-Python: >=3.6
Requires-Dist: requests
Requires-Dist: urllib3
Requires-Dist: beautifulsoup4
